pyDocsis-0.3.39.data/scripts/cm_decode
pyDocsis-0.3.39.data/scripts/mib-json-builder.py
pyDocsis-0.3.39.data/scripts/mta_decode
pydocsis/MTATlvs.py
pydocsis/MtaConfig.py
pydocsis/TLV.py
pydocsis/__init__.py
pydocsis/cmConfig.py
pydocsis/configFile.py
pydocsis/docsisTlvs.py
pydocsis/mib.py
pydocsis/mtaMibs.py
pyDocsis-0.3.39.dist-info/LICENSE
pyDocsis-0.3.39.dist-info/METADATA
pyDocsis-0.3.39.dist-info/WHEEL
pyDocsis-0.3.39.dist-info/top_level.txt
pyDocsis-0.3.39.dist-info/RECORD
