Metadata-Version: 2.1
Name: pyDocsis
Version: 0.3.39
Summary: A library for working with docsis files
Home-page: https://github.com/botheredtodd/pyDocsis
Author: Todd Balsley and Yu X
Author-email: todd.balsley@cox.com
License: Apache License 2.0
License-File: LICENSE
